Projects/ALU/rtl/ALU.v
module bit4_ALU ( // Arithmetic Logic Unit
    input [3:0] A, B,
    input [2:0] Op,
    output reg [3:0] Q,
    output reg Carry
);
    parameter ADD = 3'b000;     // Carry, A + B
    parameter SUB = 3'b001;     // A - B
    parameter AND = 3'b010;     // A & B
    parameter OR = 3'b011;      // A | B
    parameter XOR = 3'b100;     // A ^ B
    parameter NOTA = 3'b101;    // ~A
    parameter SHLA = 3'b110;    // Carry, Shift Left A
    parameter SHRA = 3'b111;    // Carry, Shift Right A

    always @(*) begin
        case (Op)
            ADD: begin
                {Carry, Q} = A + B;
            end
            SUB: begin
                Q = A - B;
                Carry = 0;
            end
            AND: begin
                Q = A & B;
                Carry = 0;
            end
            OR: begin
                Q = A | B;
                Carry = 0;
            end
            XOR: begin
                Q = A ^ B;
                Carry = 0;
            end
            NOTA: begin
                Q = ~A;
                Carry = 0;
            end
            SHLA: begin
                Q = A << 1;
                Carry = A[3];
            end
            SHRA: begin
                Q = A >> 1;
                Carry = A[0];
            end
            default: begin
                Q = 4'b0000;
                Carry = 1'b0;
            end
        endcase
    end
endmodule

Projects/ALU/tb/ALU_tb.v
`timescale 1ns/1ps

module bit4_ALU_tb;

    reg [3:0] A, B;
    reg [2:0] Op;

    wire [3:0] Q;
    wire Carry;

    bit4_ALU DUT (
        .A(A),
        .B(B),
        .Op(Op),
        .Q(Q),
        .Carry(Carry)
    );

    initial begin

        $dumpfile("sim/wave.vcd");
        $dumpvars(0, bit4_ALU_tb);
        $monitor("Op = %b A = %b B = %b / Carry = %b Q = %b", Op, A, B, Carry, Q);
        
            A = 4'd3; B = 4'd2; Op = 3'b000; // ADD
        #10 A = 4'd15; B = 4'd1; Op = 3'b000; // ADD (Carry)

        #10 A = 4'd8; B = 4'd3; Op = 3'b001; // SUB 
        #10 A = 4'd3; B = 4'd5; Op = 3'b001; // SUB (Negative Result)

        #10 A = 4'b1010; B = 4'b1100; Op = 3'b010; // AND
        #10 A = 4'b1010; B = 4'b1100; Op = 3'b011; // OR
        #10 A = 4'b1010; B = 4'b1100; Op = 3'b100; // XOR
        #10 A = 4'b1010; Op = 3'b101; // NOT

        #10 A = 4'b1001; Op = 3'b110; // Shift Left
        #10 A = 4'b1001; Op = 3'b111; // Shift Right

        #10 $finish;

    end

endmodule

Projects/ALU/sim/wave.vcd
$date
	Thu Jul 23 14:02:49 2026
$end
$version
	Icarus Verilog
$end
$timescale
	1ps
$end
$scope module bit4_ALU_tb $end
$var wire 4 ! Q [3:0] $end
$var wire 1 " Carry $end
$var reg 4 # A [3:0] $end
$var reg 4 $ B [3:0] $end
$var reg 3 % Op [2:0] $end
$scope module DUT $end
$var wire 4 & A [3:0] $end
$var wire 4 ' B [3:0] $end
$var wire 3 ( Op [2:0] $end
$var parameter 3 ) ADD $end
$var parameter 3 * AND $end
$var parameter 3 + NOTA $end
$var parameter 3 , OR $end
$var parameter 3 - SHLA $end
$var parameter 3 . SHRA $end
$var parameter 3 / SUB $end
$var parameter 3 0 XOR $end
$var reg 1 " Carry $end
$var reg 4 1 Q [3:0] $end
$upscope $end
$upscope $end
$enddefinitions $end
$comment Show the parameter values. $end
$dumpall
b100 0
b1 /
b111 .
b110 -
b11 ,
b101 +
b10 *
b0 )
$end
#0
$dumpvars
b101 1
b0 (
b10 '
b11 &
b0 %
b10 $
b11 #
0"
b101 !
$end
#10000
1"
b0 !
b0 1
b1 $
b1 '
b1111 #
b1111 &
#20000
0"
b101 !
b101 1
b1 %
b1 (
b11 $
b11 '
b1000 #
b1000 &
#30000
b1110 !
b1110 1
b101 $
b101 '
b11 #
b11 &
#40000
b1000 !
b1000 1
b10 %
b10 (
b1100 $
b1100 '
b1010 #
b1010 &
#50000
b1110 !
b1110 1
b11 %
b11 (
#60000
b110 !
b110 1
b100 %
b100 (
#70000
b101 !
b101 1
b101 %
b101 (
#80000
1"
b10 !
b10 1
b110 %
b110 (
b1001 #
b1001 &
#90000
b100 !
b100 1
b111 %
b111 (
